fastapi_create/__init__.py
fastapi_create/alembic_setup.py
fastapi_create/config_setup.py
fastapi_create/constants.py
fastapi_create/database_setup.py
fastapi_create/dependency_setup.py
fastapi_create/main.py
fastapi_create/main_setup.py
fastapi_create/manage_setup.py
fastapi_create/project_setup.py
fastapi_create/readme_setup.py
fastapi_create/requirements_setup.py
fastapi_create/utils.py
fastapi_create/templates/README_template.md.jinja2
fastapi_create/templates/alembic_env_template.py.jinja2
fastapi_create/templates/core_config_template.py.jinja2
fastapi_create/templates/db_config_template.py.jinja2
fastapi_create/templates/init_db_template.py.jinja2
fastapi_create/templates/main_template.py.jinja2
fastapi_create/templates/manage_template.py.jinja2
fastapi_create/templates/models_template.py.jinja2
fastapi_create-0.1.1.dist-info/LICENSE
fastapi_create-0.1.1.dist-info/METADATA
fastapi_create-0.1.1.dist-info/WHEEL
fastapi_create-0.1.1.dist-info/entry_points.txt
fastapi_create-0.1.1.dist-info/top_level.txt
fastapi_create-0.1.1.dist-info/RECORD
