Metadata-Version: 2.2
Name: fastapi-create
Version: 0.1.1
Summary: A CLI tool to scaffold FastAPI projects with database and migration support
Author-email: OluwaFavour <your.email@example.com>
License: MIT License
Project-URL: Homepage, https://github.com/OluwaFavour/fastapi-create
Project-URL: Repository, https://github.com/OluwaFavour/fastapi-create
Project-URL: Issues, https://github.com/OluwaFavour/fastapi-create/issues
Requires-Python: >=3.8
License-File: LICENSE
Requires-Dist: click>=8.1.8
Requires-Dist: colorama>=0.4.6
Requires-Dist: Jinja2>=3.1.6
Requires-Dist: markdown-it-py>=3.0.0
Requires-Dist: MarkupSafe>=3.0.2
Requires-Dist: mdurl>=0.1.2
Requires-Dist: Pygments>=2.19.1
Requires-Dist: python-dotenv>=1.0.1
Requires-Dist: rich>=13.9.4
Requires-Dist: shellingham>=1.5.4
Requires-Dist: typer>=0.15.2
Requires-Dist: typing_extensions>=4.12.2
